{
    "prepare_queue": {
        "installed": [],
        "uninstalled": []
    },
    "config_munge": {
        "files": {}
    },
    "installed_plugins": {
        "cordova-plugin-camera": {
            "PACKAGE_NAME": "com.theparcl.v1"
        },
        "cordova-plugin-device": {
            "PACKAGE_NAME": "com.theparcl.v1"
        },
        "cordova-plugin-fullscreen": {
            "PACKAGE_NAME": "com.theparcl.v1"
        },
        "cordova-plugin-geolocation": {
            "PACKAGE_NAME": "com.theparcl.v1"
        },
        "cordova-plugin-inappbrowser": {
            "PACKAGE_NAME": "com.theparcl.v1"
        },
        "cordova-plugin-network-information": {
            "PACKAGE_NAME": "com.theparcl.v1"
        },
        "cordova-plugin-sim": {
            "PACKAGE_NAME": "com.theparcl.v1"
        },
        "cordova-plugin-statusbar": {
            "PACKAGE_NAME": "com.theparcl.v1"
        },
        "cordova-plugin-vibration": {
            "PACKAGE_NAME": "com.theparcl.v1"
        },
        "cordova-plugin-whitelist": {
            "PACKAGE_NAME": "com.theparcl.v1"
        },
        "cordova-universal-links-plugin": {
            "PACKAGE_NAME": "com.theparcl.v1"
        },
        "ionic-plugin-keyboard": {
            "PACKAGE_NAME": "com.theparcl.v1"
        },
        "cordova-plugin-googlemaps": {
            "API_KEY_FOR_ANDROID": "AIzaSyDpajAUICmsESNG_aWaUHi66zXyeM4a9kg",
            "PACKAGE_NAME": "com.theparcl.v1"
        }
    },
    "dependent_plugins": {
        "cordova-plugin-compat": {
            "PACKAGE_NAME": "com.theparcl.v1"
        }
    }
}